nationality_predictor/__init__.py
nationality_predictor/nationality_predictor.py
nationality_predictor-1.4.1.dist-info/LICENSE
nationality_predictor-1.4.1.dist-info/METADATA
nationality_predictor-1.4.1.dist-info/WHEEL
nationality_predictor-1.4.1.dist-info/top_level.txt
nationality_predictor-1.4.1.dist-info/RECORD
