Metadata-Version: 2.1
Name: nationality-predictor
Version: 1.4.1
Summary: An engine that predicts the nationality of a person's name
Home-page: https://github.com/dewittethomas/nationality-predictor
Author: Thomas Dewitte
Author-email: thomasdewittecontact@gmail.com
License: MIT
Classifier: Programming Language :: Python :: 3
Classifier: Programming Language :: Python :: 3.8
Classifier: Operating System :: OS Independent
Classifier: License :: OSI Approved :: MIT License
License-File: LICENSE
Requires-Dist: requests (>=2.28.1)
